frontier_signal/__init__.py
frontier_signal/_version.py
frontier_signal/async_client.py
frontier_signal/client.py
frontier_signal/exceptions.py
frontier_signal/schemas.py
frontier_signal-0.1.0.dist-info/licenses/LICENSE
frontier_signal-0.1.0.dist-info/METADATA
frontier_signal-0.1.0.dist-info/WHEEL
frontier_signal-0.1.0.dist-info/top_level.txt
frontier_signal-0.1.0.dist-info/RECORD
